SpriteSheet_kyquan/__init__.py
SpriteSheet_kyquan/spriteutil.py
SpriteSheet_kyquan-1.0.4.dist-info/LICENSE.md
SpriteSheet_kyquan-1.0.4.dist-info/METADATA
SpriteSheet_kyquan-1.0.4.dist-info/WHEEL
SpriteSheet_kyquan-1.0.4.dist-info/top_level.txt
SpriteSheet_kyquan-1.0.4.dist-info/RECORD
