Metadata-Version: 2.1
Name: SpriteSheet-kyquan
Version: 1.0.4
Summary: A small example package
Home-page: https://github.com/intek-training-jsc/sprite-sheet-kyquanlx
Author: Ho Ky Quan
Author-email: quan.ho@f4.intek.edu.vn
License: UNKNOWN
Platform: UNKNOWN
Classifier: Programming Language :: Python :: 3
Classifier: License :: OSI Approved :: MIT License
Classifier: Operating System :: OS Independent
Requires-Python: >=3.6
